torchrecurrent/__init__.py
torchrecurrent/base.py
torchrecurrent/benchmarks/__init__.py
torchrecurrent/benchmarks/adding.py
torchrecurrent/benchmarks/copymemory.py
torchrecurrent/cells/__init__.py
torchrecurrent/cells/antisymmetricrnn_cell.py
torchrecurrent/cells/atr_cell.py
torchrecurrent/cells/br_cell.py
torchrecurrent/cells/cfn_cell.py
torchrecurrent/cells/cornn_cell.py
torchrecurrent/cells/fastrnn_cell.py
torchrecurrent/cells/indrnn_cell.py
torchrecurrent/cells/janet_cell.py
torchrecurrent/cells/lem_cell.py
torchrecurrent/cells/lightru_cell.py
torchrecurrent/cells/ligru_cell.py
torchrecurrent/cells/mgu_cell.py
torchrecurrent/cells/multiplicativelstm_cell.py
torchrecurrent/cells/mut_cell.py
torchrecurrent/cells/nas_cell.py
torchrecurrent/cells/originallstm_cell.py
torchrecurrent/cells/peepholelstm_cell.py
torchrecurrent/cells/ran_cell.py
torchrecurrent/cells/rhn_cell.py
torchrecurrent/cells/scrn_cell.py
torchrecurrent/cells/sgrn_cell.py
torchrecurrent/cells/star_cell.py
torchrecurrent/cells/ugrnn_cell.py
torchrecurrent/cells/unicornn_cell.py
torchrecurrent/cells/wmclstm_cell.py
torchrecurrent-0.1.11.dist-info/licenses/LICENSE
torchrecurrent-0.1.11.dist-info/METADATA
torchrecurrent-0.1.11.dist-info/WHEEL
torchrecurrent-0.1.11.dist-info/top_level.txt
torchrecurrent-0.1.11.dist-info/RECORD
